papfa/__init__.py
papfa/cli.py
papfa/config.py
papfa/consumers.py
papfa/dtos.py
papfa/papfa.py
papfa/producers.py
papfa/settings.py
papfa/utils.py
papfa/middlewares/__init__.py
papfa/middlewares/consumer.py
papfa/middlewares/producer.py
tests/__init__.py
tests/test_consumer.py
papfa-0.1.19.dist-info/LICENSE
papfa-0.1.19.dist-info/METADATA
papfa-0.1.19.dist-info/WHEEL
papfa-0.1.19.dist-info/entry_points.txt
papfa-0.1.19.dist-info/top_level.txt
papfa-0.1.19.dist-info/RECORD
