Metadata-Version: 2.1
Name: papfa
Version: 0.1.19
Summary: High level pub/sub package
Home-page: https://github.com/kamyab98/papfa
Author: Kamyab Zareh
Author-email: kamyab.zareh@gmail.com
License: MIT license
Keywords: papfa
Platform: UNKNOWN
Classifier: Development Status :: 2 - Pre-Alpha
Classifier: Intended Audience :: Developers
Classifier: License :: OSI Approved :: MIT License
Classifier: Natural Language :: English
Classifier: Programming Language :: Python :: 3
Classifier: Programming Language :: Python :: 3.7
Classifier: Programming Language :: Python :: 3.8
Classifier: Programming Language :: Python :: 3.9
Classifier: Programming Language :: Python :: 3.10
Classifier: Programming Language :: Python :: 3.11
Requires-Python: >=3.7
License-File: LICENSE
Requires-Dist: confluent-kafka[avro] (~=2.1.1)
Requires-Dist: dataclasses-avroschema (~=0.43.9)
Requires-Dist: click (~=8.1.3)
